<annotations><filename>00001113.JPEG</filename><folder>images</folder><size><width>224</width><height>224</height><depth>3</depth></size><object><name>lego gubbe</name><pose>Unspecified</pose><truncated>0</truncated><difficult>0</difficult><bndbox><xmin>23</xmin><ymin>95</ymin><xmax>82</xmax><ymax>155</ymax></bndbox></object><object><name>lego gubbe</name><pose>Unspecified</pose><truncated>0</truncated><difficult>0</difficult><bndbox><xmin>157</xmin><ymin>70</ymin><xmax>194</xmax><ymax>134</ymax></bndbox></object><object><name>lego gubbe</name><pose>Unspecified</pose><truncated>0</truncated><difficult>0</difficult><bndbox><xmin>19</xmin><ymin>6</ymin><xmax>61</xmax><ymax>47</ymax></bndbox></object></annotations>