<annotations><filename>00004423.JPEG</filename><folder>images</folder><size><width>224</width><height>224</height><depth>3</depth></size><object><name>lego gubbe</name><pose>Unspecified</pose><truncated>0</truncated><difficult>0</difficult><bndbox><xmin>26</xmin><ymin>132</ymin><xmax>123</xmax><ymax>193</ymax></bndbox></object><object><name>lego gubbe</name><pose>Unspecified</pose><truncated>0</truncated><difficult>0</difficult><bndbox><xmin>58</xmin><ymin>32</ymin><xmax>106</xmax><ymax>80</ymax></bndbox></object></annotations>