<annotations><filename>00003538.JPEG</filename><folder>images</folder><size><width>224</width><height>224</height><depth>3</depth></size><object><name>lego gubbe</name><pose>Unspecified</pose><truncated>0</truncated><difficult>0</difficult><bndbox><xmin>9</xmin><ymin>32</ymin><xmax>99</xmax><ymax>115</ymax></bndbox></object><object><name>lego gubbe</name><pose>Unspecified</pose><truncated>0</truncated><difficult>0</difficult><bndbox><xmin>153</xmin><ymin>21</ymin><xmax>198</xmax><ymax>74</ymax></bndbox></object><object><name>lego gubbe</name><pose>Unspecified</pose><truncated>0</truncated><difficult>0</difficult><bndbox><xmin>125</xmin><ymin>83</ymin><xmax>214</xmax><ymax>166</ymax></bndbox></object></annotations>