<annotations><filename>00000772.JPEG</filename><folder>images</folder><size><width>224</width><height>224</height><depth>3</depth></size><object><name>lego gubbe</name><pose>Unspecified</pose><truncated>0</truncated><difficult>0</difficult><bndbox><xmin>104</xmin><ymin>50</ymin><xmax>212</xmax><ymax>157</ymax></bndbox></object><object><name>lego gubbe</name><pose>Unspecified</pose><truncated>0</truncated><difficult>0</difficult><bndbox><xmin>24</xmin><ymin>110</ymin><xmax>51</xmax><ymax>138</ymax></bndbox></object><object><name>lego gubbe</name><pose>Unspecified</pose><truncated>0</truncated><difficult>0</difficult><bndbox><xmin>4</xmin><ymin>66</ymin><xmax>30</xmax><ymax>94</ymax></bndbox></object></annotations>