<annotations><filename>00002261.JPEG</filename><folder>images</folder><size><width>224</width><height>224</height><depth>3</depth></size><object><name>lego gubbe</name><pose>Unspecified</pose><truncated>0</truncated><difficult>0</difficult><bndbox><xmin>82</xmin><ymin>101</ymin><xmax>163</xmax><ymax>170</ymax></bndbox></object><object><name>lego gubbe</name><pose>Unspecified</pose><truncated>0</truncated><difficult>0</difficult><bndbox><xmin>14</xmin><ymin>28</ymin><xmax>80</xmax><ymax>94</ymax></bndbox></object><object><name>lego gubbe</name><pose>Unspecified</pose><truncated>0</truncated><difficult>0</difficult><bndbox><xmin>170</xmin><ymin>124</ymin><xmax>220</xmax><ymax>161</ymax></bndbox></object></annotations>