<annotations><filename>00001838.JPEG</filename><folder>images</folder><size><width>224</width><height>224</height><depth>3</depth></size><object><name>lego gubbe</name><pose>Unspecified</pose><truncated>0</truncated><difficult>0</difficult><bndbox><xmin>117</xmin><ymin>141</ymin><xmax>186</xmax><ymax>203</ymax></bndbox></object><object><name>lego gubbe</name><pose>Unspecified</pose><truncated>0</truncated><difficult>0</difficult><bndbox><xmin>8</xmin><ymin>67</ymin><xmax>111</xmax><ymax>170</ymax></bndbox></object><object><name>lego gubbe</name><pose>Unspecified</pose><truncated>0</truncated><difficult>0</difficult><bndbox><xmin>118</xmin><ymin>92</ymin><xmax>153</xmax><ymax>125</ymax></bndbox></object></annotations>